to_file_like_obj/__init__.py
to_file_like_obj/py.typed
to_file_like_obj-0.0.7.dist-info/METADATA
to_file_like_obj-0.0.7.dist-info/WHEEL
to_file_like_obj-0.0.7.dist-info/licenses/LICENSE
to_file_like_obj-0.0.7.dist-info/RECORD
