Metadata-Version: 2.3
Name: to-file-like-obj
Version: 0.0.7
Summary: Utility function to convert an iterable of bytes or str to a readable file-like object.
Project-URL: Source, https://github.com/uktrade/to-file-like-obj
Author-email: Department for Business and Trade <sre@digital.trade.gov.uk>
License-File: LICENSE
Classifier: License :: OSI Approved :: MIT License
Classifier: Operating System :: OS Independent
Classifier: Programming Language :: Python :: 3
Requires-Python: >=3.7
Provides-Extra: ci
Requires-Dist: coverage; extra == 'ci'
Requires-Dist: mypy<1.5; extra == 'ci'
Requires-Dist: pytest; extra == 'ci'
Requires-Dist: pytest-cov; extra == 'ci'
Provides-Extra: dev
Requires-Dist: mypy<1.5; extra == 'dev'
Requires-Dist: pytest>=7.2.1; extra == 'dev'
